README.txt
setup.cfg
setup.py
pyogp/__init__.py
pyogp.lib.base.egg-info/PKG-INFO
pyogp.lib.base.egg-info/SOURCES.txt
pyogp.lib.base.egg-info/dependency_links.txt
pyogp.lib.base.egg-info/namespace_packages.txt
pyogp.lib.base.egg-info/not-zip-safe
pyogp.lib.base.egg-info/requires.txt
pyogp.lib.base.egg-info/top_level.txt
pyogp/lib/__init__.py
pyogp/lib/base/__init__.py
pyogp/lib/base/caps.py
pyogp/lib/base/datatypes.py
pyogp/lib/base/event_queue.py
pyogp/lib/base/events.py
pyogp/lib/base/exc.py
pyogp/lib/base/helpers.py
pyogp/lib/base/message_manager.py
pyogp/lib/base/settings.py
pyogp/lib/base/message/__init__.py
pyogp/lib/base/message/circuit.py
pyogp/lib/base/message/data_packer.py
pyogp/lib/base/message/data_unpacker.py
pyogp/lib/base/message/factory.py
pyogp/lib/base/message/llsd_builder.py
pyogp/lib/base/message/llsd_sender.py
pyogp/lib/base/message/message.py
pyogp/lib/base/message/message_dot_xml.py
pyogp/lib/base/message/message_handler.py
pyogp/lib/base/message/msgtypes.py
pyogp/lib/base/message/template.py
pyogp/lib/base/message/template_dict.py
pyogp/lib/base/message/template_parser.py
pyogp/lib/base/message/udpdeserializer.py
pyogp/lib/base/message/udpdispatcher.py
pyogp/lib/base/message/udpserializer.py
pyogp/lib/base/message/data/__init__.py
pyogp/lib/base/message/tests/__init__.py
pyogp/lib/base/message/tests/packet_test.py
pyogp/lib/base/message/tests/test_circuits.py
pyogp/lib/base/message/tests/test_llsd_builder.py
pyogp/lib/base/message/tests/test_message_dot_xml.py
pyogp/lib/base/message/tests/test_message_wrapper.py
pyogp/lib/base/message/tests/test_packetdata.py
pyogp/lib/base/message/tests/test_template_parser.py
pyogp/lib/base/message/tests/test_udp_deserializer.py
pyogp/lib/base/message/tests/test_udp_serializer.py
pyogp/lib/base/message/tests/test_udpconnection.py
pyogp/lib/base/network/__init__.py
pyogp/lib/base/network/net.py
pyogp/lib/base/network/stdlib_client.py
pyogp/lib/base/network/tests/__init__.py
pyogp/lib/base/network/tests/mockup_client.py
pyogp/lib/base/network/tests/mockup_net.py
pyogp/lib/base/network/tests/testDocTests.py
pyogp/lib/base/tests/__init__.py
pyogp/lib/base/tests/base.py
pyogp/lib/base/tests/config.py
pyogp/lib/base/tests/mock_xmlrpc.py
pyogp/lib/base/tests/mockup_client.py
