Metadata-Version: 1.0
Name: pyogp.lib.base
Version: 0.1
Summary: basic pyogp library package
Home-page: http://wiki.secondlife.com/wiki/Pyogp
Author: Pyogp collective
Author-email: pyogp@lists.lindenlab.com
License: Apache2
Keywords: pyogp login awg virtualworlds
Platform: UNKNOWN
Classifier: Programming Language :: Python
Classifier: Topic :: Software Development :: Libraries :: Python Modules
